{
  "parent": "minecraft:recipes/root",
  "criteria": {
    "has_the_recipe": {
      "conditions": {
        "recipe": "extradelight:gingham_orange"
      },
      "trigger": "minecraft:recipe_unlocked"
    },
    "orange_gingham": {
      "conditions": {
        "items": [
          {
            "items": "minecraft:white_wool"
          }
        ]
      },
      "trigger": "minecraft:inventory_changed"
    }
  },
  "requirements": [
    [
      "has_the_recipe",
      "orange_gingham"
    ]
  ],
  "rewards": {
    "recipes": [
      "extradelight:gingham_orange"
    ]
  }
}